CHANGELOG.md
MANIFEST.in
README.md
requirements.txt
setup.cfg
setup.py
test-requirements.txt
version.txt
sap_py_jwt.egg-info/PKG-INFO
sap_py_jwt.egg-info/SOURCES.txt
sap_py_jwt.egg-info/dependency_links.txt
sap_py_jwt.egg-info/entry_points.txt
sap_py_jwt.egg-info/requires.txt
sap_py_jwt.egg-info/top_level.txt
sapjwt/__init__.py
sapjwt/jwtValidation.py
sapjwt/deps/__init__.py
sapjwt/deps/darwin/x64/libsapssoext.dylib
sapjwt/deps/linux/__init__.py
sapjwt/deps/linux/ppc64/libsapssoext.so
sapjwt/deps/linux/ppc64le/libsapssoext.so
sapjwt/deps/linux/x64/__init__.py
sapjwt/deps/linux/x64/libsapssoext.so
sapjwt/deps/win32/x64/sapssoext.dll